SmartBudget/__init__.py
SmartBudget/analysis.py
SmartBudget/budget.py
SmartBudget/transactions.py
tests/__init__.py
tests/test_analysis.py
tests/test_budget.py
tests/test_transactions.py
SmartBudget-0.0.3.1.dist-info/LICENSE.txt
SmartBudget-0.0.3.1.dist-info/METADATA
SmartBudget-0.0.3.1.dist-info/WHEEL
SmartBudget-0.0.3.1.dist-info/top_level.txt
SmartBudget-0.0.3.1.dist-info/RECORD
