Metadata-Version: 2.1
Name: SmartBudget
Version: 0.0.3.1
Summary: Бибилиотека для удобного управления финансами, анализом расходов и бюджетированием
Author: 
Author-email: 1sergeiivanov1@mail.ru
Classifier: Programming Language :: Python :: 3
Classifier: License :: OSI Approved :: MIT License
Classifier: Operating System :: OS Independent
Requires-Python: >=3.6
License-File: LICENSE.txt
